[{
    "title": "Dijual Rumah Sutorejo Utara Minimalis Siap Huni",
    "address": "Sutorejo Utara",
    "description": "*Dijual Rumah Sutorejo Utara Minimalis Siap Huni* \n\nLuas Tanah 156 mÂ² (9 x 17,5) \nLuas Bangunan 256 m^2 \nKamar Tidur 4 +1 (2 KM dalam) \nKamar Mandi 3+1 \n\nCarport 2 mobil \nListrik 5500w \nPDAM \n\nHadap Utara \n\n+ Dekat dari Raya Mulyosari \n+ Hanya 300m dari Superindo Mulyosari \n+ Include kitchen set 7 AC, water heater, 2 pompa air, tandon atas & bawah \n+ Master Bedroom luas dengan Walk-in Closet dan kamar mandi dalam (bathtub+shower) \n+ Sanitary Wasser + Toto \n+ Lantai Granit Tile + Lantai Kayu (Solid Kayu Deluxe) \n\nSerifikat Hak Milik (SHM) \n\nHarga 3,050 Milyar Nego \n\nHubungi: \nCaesar Go \nXM Darmo \n081 233 233 535 \nwa.me/6281233233535",
    "price": 3050000000,
    "lotSize": 156,
    "buildingSize": 256,
    "carCount": 2,
    "bedroomCount": 5,
    "bathroomCount": 4,
    "floorCount": 0,
    "electricPower" : 5500,
    "facing": "utara",
    "ownership": "SHM",
    "city": "",
    "pictureUrls": [],
    "contact": {
        "name": "Caesar Go",
        "phoneNumber": "081233233535",
        "profilePictureURL": "",
        "sourceURL": "",
        "provider": "XM Darmo"
    },
    "coordinate": {
        "latitude": "",
        "longitude": ""
    }
}]